desktop/org.fuentelibre.gtk_llm_Applet.desktop
desktop/org.fuentelibre.gtk_llm_Chat.desktop
gtk_llm_chat/__init__.py
gtk_llm_chat/_version.py
gtk_llm_chat/chat_application.py
gtk_llm_chat/chat_sidebar.py
gtk_llm_chat/chat_window.py
gtk_llm_chat/db_operations.py
gtk_llm_chat/debug_utils.py
gtk_llm_chat/llm_client.py
gtk_llm_chat/llm_gui.py
gtk_llm_chat/main.py
gtk_llm_chat/markdownview.py
gtk_llm_chat/model_selection.py
gtk_llm_chat/model_selector.py
gtk_llm_chat/platform_utils.py
gtk_llm_chat/python313_compatibility.py
gtk_llm_chat/resource_manager.py
gtk_llm_chat/single_instance.py
gtk_llm_chat/style_manager.py
gtk_llm_chat/tray_applet.py
gtk_llm_chat/welcome.py
gtk_llm_chat/wide_model_selector.py
gtk_llm_chat/widgets.py
gtk_llm_chat/hicolor/icon-theme.cache
gtk_llm_chat/hicolor/index.theme
gtk_llm_chat/hicolor/256x256/apps/org.fuentelibre.gtk_llm_Chat.png
gtk_llm_chat/hicolor/48x48/apps/org.fuentelibre.gtk_llm_Chat-symbolic.png
gtk_llm_chat/hicolor/scalable/actions/checkmark-symbolic.svg
gtk_llm_chat/hicolor/scalable/devices/brain-augmented-symbolic.svg
gtk_llm_chat/hicolor/scalable/devices/brain-symbolic.svg
gtk_llm_chat/hicolor/scalable/devices/open-book-symbolic.svg
gtk_llm_chat/hicolor/scalable/devices/padlock2-open-symbolic.svg
gtk_llm_chat/hicolor/scalable/devices/padlock2-symbolic.svg
gtk_llm_chat/hicolor/symbolic/apps/org.fuentelibre.gtk_llm_Chat-symbolic.svg
gtk_llm_chat-4.0.5.dist-info/licenses/LICENSE
po/de/LC_MESSAGES/gtk-llm-chat.mo
po/es/LC_MESSAGES/gtk-llm-chat.mo
po/pt/LC_MESSAGES/gtk-llm-chat.mo
po/zh/LC_MESSAGES/gtk-llm-chat.mo
gtk_llm_chat-4.0.5.dist-info/METADATA
gtk_llm_chat-4.0.5.dist-info/WHEEL
gtk_llm_chat-4.0.5.dist-info/entry_points.txt
gtk_llm_chat-4.0.5.dist-info/top_level.txt
gtk_llm_chat-4.0.5.dist-info/RECORD
