Metadata-Version: 2.4
Name: gtk-llm-chat
Version: 4.0.5
Summary: A GTK graphical interface for chatting with large language models (LLMs)
Author-email: Sebastian Silva <sebastian@fuentelibre.org>
License-Expression: GPL-3.0-or-later
Project-URL: Homepage, https://gtk-llm-chat.fuentelibre.org/
Project-URL: Issues, https://github.com/icarito/gtk_llm_chat/issues
Project-URL: Repository, https://github.com/icarito/gtk_llm_chat.git
Keywords: gtk,chat,llm,ai,openai,gemini,groq,grok,deepseek,perplexity,anthropic,openrouter
Classifier: Programming Language :: Python :: 3
Classifier: Operating System :: OS Independent
Requires-Python: >=3.8
License-File: LICENSE
Requires-Dist: pygobject
Requires-Dist: llm
Requires-Dist: llm-gemini
Requires-Dist: llm-groq
Requires-Dist: llm-grok
Requires-Dist: llm-deepseek
Requires-Dist: llm-perplexity
Requires-Dist: llm-anthropic
Requires-Dist: llm-openrouter
Requires-Dist: markdown-it-py
Requires-Dist: python-ulid
Requires-Dist: pystray-freedesktop>=0.19.6a1; sys_platform == "linux"
Requires-Dist: watchdog
Requires-Dist: pyxdg; sys_platform == "linux"
Requires-Dist: pystray; sys_platform == "darwin"
Requires-Dist: pystray; sys_platform == "win32"
Dynamic: license-file
